{"stats":{"minecraft:mined":{"minecraft:oak_log":1,"minecraft:oak_leaves":3},"minecraft:custom":{"minecraft:jump":79,"minecraft:leave_game":1,"minecraft:time_since_rest":119,"minecraft:deaths":1,"minecraft:damage_dealt":9,"minecraft:damage_taken":225,"minecraft:sprint_one_cm":2572,"minecraft:play_time":2942,"minecraft:time_since_death":0,"minecraft:walk_one_cm":5804,"minecraft:total_world_time":2942,"minecraft:fall_one_cm":1254,"minecraft:fly_one_cm":7538},"minecraft:used":{"minecraft:oak_log":1},"minecraft:killed_by":{"minecraft:zombie":1},"minecraft:picked_up":{"minecraft:oak_log":1}},"DataVersion":3953}